CHANGELOG
MANIFEST.in
README.md
main.py
requirements.txt
setup.cfg
setup.py
tests/__init__.py
tweebot/__init__.py
tweebot/client.py
tweebot/commands.py
tweebot/console.py
tweebot/keys.py
tweebot.egg-info/PKG-INFO
tweebot.egg-info/SOURCES.txt
tweebot.egg-info/dependency_links.txt
tweebot.egg-info/entry_points.txt
tweebot.egg-info/requires.txt
tweebot.egg-info/top_level.txt