Metadata-Version: 1.1
Name: tweebot
Version: 0.2.1
Summary: A simple twitter-bot command-line tool and library
Home-page: https://github.com/kcsaff/tweebot
Author: K.C.Saff
Author-email: kc@saff.net
License: MIT
Platform: UNKNOWN
Classifier: License :: OSI Approved :: MIT License
Classifier: Intended Audience :: Other Audience
Classifier: Programming Language :: Python :: 3
